zope/structuredtext/__init__.py
zope/structuredtext/docbook.py
zope/structuredtext/document.py
zope/structuredtext/html.py
zope/structuredtext/stdom.py
zope/structuredtext/stletters.py
zope/structuredtext/stng.py
zope/structuredtext/tests.py
zope/structuredtext/regressions/Acquisition.ref
zope/structuredtext/regressions/Acquisition.stx
zope/structuredtext/regressions/Acquisition.xml
zope/structuredtext/regressions/ExtensionClass.ref
zope/structuredtext/regressions/ExtensionClass.stx
zope/structuredtext/regressions/ExtensionClass.xml
zope/structuredtext/regressions/InnerLinks.ref
zope/structuredtext/regressions/InnerLinks.stx
zope/structuredtext/regressions/InnerLinks.xml
zope/structuredtext/regressions/Links.ref
zope/structuredtext/regressions/Links.stx
zope/structuredtext/regressions/Links.xml
zope/structuredtext/regressions/MultiMapping.ref
zope/structuredtext/regressions/MultiMapping.stx
zope/structuredtext/regressions/MultiMapping.xml
zope/structuredtext/regressions/examples.ref
zope/structuredtext/regressions/examples.stx
zope/structuredtext/regressions/examples.xml
zope/structuredtext/regressions/examples1.ref
zope/structuredtext/regressions/examples1.stx
zope/structuredtext/regressions/examples1.xml
zope/structuredtext/regressions/header_example.ref
zope/structuredtext/regressions/header_example.stx
zope/structuredtext/regressions/header_example.xml
zope/structuredtext/regressions/images.ref
zope/structuredtext/regressions/images.stx
zope/structuredtext/regressions/images.xml
zope/structuredtext/regressions/index.ref
zope/structuredtext/regressions/index.stx
zope/structuredtext/regressions/index.xml
zope/structuredtext/regressions/numbered_example.ref
zope/structuredtext/regressions/numbered_example.stx
zope/structuredtext/regressions/numbered_example.xml
zope/structuredtext/regressions/table.ref
zope/structuredtext/regressions/table.stx
zope_structuredtext-6.0.dist-info/licenses/LICENSE.txt
zope_structuredtext-6.0.dist-info/METADATA
zope_structuredtext-6.0.dist-info/WHEEL
zope_structuredtext-6.0.dist-info/top_level.txt
zope_structuredtext-6.0.dist-info/RECORD
